{"train_loss": 0.34513556957244873, "val_loss": 0.6877079606056213, "val_accuracy": 0.7068750262260437, "val_f1_score": 0.7293710112571716, "val_f2_score": 0.8395324349403381, "val_f3_score": 0.8840397000312805, "val_negative_predictive_value": 0.9172794222831726, "val_positive_predictive_value": 0.5984848737716675, "val_roc_auc": 0.8647496700286865, "val_sensitivity": 0.9335302710533142, "val_specificity": 0.5406283736228943, "epoch": 0, "step": 500, "timestamp": 1760714799, "checkpoint_dir_name": "checkpoint_000000", "should_checkpoint": true, "done": false, "training_iteration": 1, "trial_id": "a46a968f", "date": "2025-10-17_18-26-42", "time_this_iter_s": 391.3871877193451, "time_total_s": 391.3871877193451, "pid": 337935, "hostname": "alex-MS-7996", "node_ip": "192.168.1.241", "config": {"train_loop_config": {"learning_rate": 5.822477020628017e-06, "batch_size": 2, "tile_config": "TileConfig(size=TileSize(width=50, height=50), overlap=25)"}}, "time_since_restore": 391.3871877193451, "iterations_since_restore": 1}
{"train_loss": 0.10742039233446121, "val_loss": 0.5240951776504517, "val_accuracy": 0.8374999761581421, "val_f1_score": 0.8082596063613892, "val_f2_score": 0.8089755177497864, "val_f3_score": 0.8092144131660461, "val_negative_predictive_value": 0.8599348664283752, "val_positive_predictive_value": 0.8070692420005798, "val_roc_auc": 0.9211052656173706, "val_sensitivity": 0.8094534873962402, "val_specificity": 0.858071506023407, "train_accuracy": 0.5899999737739563, "train_f1_score": 0.7024673223495483, "train_f2_score": 0.8373702168464661, "train_f3_score": 0.8946395516395569, "train_negative_predictive_value": 0.841269850730896, "train_positive_predictive_value": 0.5537757277488708, "train_roc_auc": 0.7101014256477356, "train_sensitivity": 0.9603174328804016, "train_specificity": 0.21370968222618103, "epoch": 1, "step": 1000, "timestamp": 1760715053, "checkpoint_dir_name": "checkpoint_000001", "should_checkpoint": true, "done": false, "training_iteration": 2, "trial_id": "a46a968f", "date": "2025-10-17_18-30-55", "time_this_iter_s": 253.27339720726013, "time_total_s": 644.6605849266052, "pid": 337935, "hostname": "alex-MS-7996", "node_ip": "192.168.1.241", "config": {"train_loop_config": {"learning_rate": 5.822477020628017e-06, "batch_size": 2, "tile_config": "TileConfig(size=TileSize(width=50, height=50), overlap=25)"}}, "time_since_restore": 644.6605849266052, "iterations_since_restore": 2}
{"train_loss": 0.04608215391635895, "val_loss": 0.4433952271938324, "val_accuracy": 0.8443750143051147, "val_f1_score": 0.8323232531547546, "val_f2_score": 0.8788396120071411, "val_f3_score": 0.89552241563797, "val_negative_predictive_value": 0.9255050420761108, "val_positive_predictive_value": 0.7648515105247498, "val_roc_auc": 0.9385889172554016, "val_sensitivity": 0.9128507971763611, "val_specificity": 0.7941495180130005, "train_accuracy": 0.8090000152587891, "train_f1_score": 0.821328341960907, "train_f2_score": 0.8738057613372803, "train_f3_score": 0.8928208351135254, "train_negative_predictive_value": 0.8980582356452942, "train_positive_predictive_value": 0.7465986609458923, "train_roc_auc": 0.9145445823669434, "train_sensitivity": 0.9126819372177124, "train_specificity": 0.712909460067749, "epoch": 2, "step": 1500, "timestamp": 1760715307, "checkpoint_dir_name": "checkpoint_000002", "should_checkpoint": true, "done": false, "training_iteration": 3, "trial_id": "a46a968f", "date": "2025-10-17_18-35-10", "time_this_iter_s": 254.5490140914917, "time_total_s": 899.2095990180969, "pid": 337935, "hostname": "alex-MS-7996", "node_ip": "192.168.1.241", "config": {"train_loop_config": {"learning_rate": 5.822477020628017e-06, "batch_size": 2, "tile_config": "TileConfig(size=TileSize(width=50, height=50), overlap=25)"}}, "time_since_restore": 899.2095990180969, "iterations_since_restore": 3}
{"train_loss": 0.22432023286819458, "val_loss": 0.41743430495262146, "val_accuracy": 0.8700000047683716, "val_f1_score": 0.851640522480011, "val_f2_score": 0.8695018887519836, "val_f3_score": 0.875623345375061, "val_negative_predictive_value": 0.9085714221000671, "val_positive_predictive_value": 0.8234483003616333, "val_roc_auc": 0.9469810724258423, "val_sensitivity": 0.8818315863609314, "val_specificity": 0.861321747303009, "train_accuracy": 0.843999981880188, "train_f1_score": 0.855555534362793, "train_f2_score": 0.8943089246749878, "train_f3_score": 0.9080188870429993, "train_negative_predictive_value": 0.9073634147644043, "train_positive_predictive_value": 0.7979274392127991, "train_roc_auc": 0.9409037828445435, "train_sensitivity": 0.9221556782722473, "train_specificity": 0.765531063079834, "epoch": 3, "step": 2000, "timestamp": 1760715559, "checkpoint_dir_name": "checkpoint_000003", "should_checkpoint": true, "done": false, "training_iteration": 4, "trial_id": "a46a968f", "date": "2025-10-17_18-39-22", "time_this_iter_s": 252.04278087615967, "time_total_s": 1151.2523798942566, "pid": 337935, "hostname": "alex-MS-7996", "node_ip": "192.168.1.241", "config": {"train_loop_config": {"learning_rate": 5.822477020628017e-06, "batch_size": 2, "tile_config": "TileConfig(size=TileSize(width=50, height=50), overlap=25)"}}, "time_since_restore": 1151.2523798942566, "iterations_since_restore": 4}
{"train_loss": 0.006389518268406391, "val_loss": 0.44547247886657715, "val_accuracy": 0.8387500047683716, "val_f1_score": 0.8315926790237427, "val_f2_score": 0.8939096331596375, "val_f3_score": 0.9168105721473694, "val_negative_predictive_value": 0.9463087320327759, "val_positive_predictive_value": 0.7450292110443115, "val_roc_auc": 0.951610803604126, "val_sensitivity": 0.9409158229827881, "val_specificity": 0.7638136744499207, "train_accuracy": 0.8600000143051147, "train_f1_score": 0.8640776872634888, "train_f2_score": 0.9041039943695068, "train_f3_score": 0.9182831048965454, "train_negative_predictive_value": 0.9284116625785828, "train_positive_predictive_value": 0.8047016263008118, "train_roc_auc": 0.953609824180603, "train_sensitivity": 0.9329140186309814, "train_specificity": 0.7934990525245667, "epoch": 4, "step": 2500, "timestamp": 1760715810, "checkpoint_dir_name": "checkpoint_000004", "should_checkpoint": true, "done": false, "training_iteration": 5, "trial_id": "a46a968f", "date": "2025-10-17_18-43-33", "time_this_iter_s": 251.25033617019653, "time_total_s": 1402.5027160644531, "pid": 337935, "hostname": "alex-MS-7996", "node_ip": "192.168.1.241", "config": {"train_loop_config": {"learning_rate": 5.822477020628017e-06, "batch_size": 2, "tile_config": "TileConfig(size=TileSize(width=50, height=50), overlap=25)"}}, "time_since_restore": 1402.5027160644531, "iterations_since_restore": 5}
{"train_loss": 0.03212864696979523, "val_loss": 0.47917014360427856, "val_accuracy": 0.8581249713897705, "val_f1_score": 0.8363374471664429, "val_f2_score": 0.8484494090080261, "val_f3_score": 0.8525650501251221, "val_negative_predictive_value": 0.8910112380981445, "val_positive_predictive_value": 0.8169013857841492, "val_roc_auc": 0.9427289962768555, "val_sensitivity": 0.8567208051681519, "val_specificity": 0.8591549396514893, "train_accuracy": 0.8949999809265137, "train_f1_score": 0.9032257795333862, "train_f2_score": 0.9326227903366089, "train_f3_score": 0.9428516626358032, "train_negative_predictive_value": 0.9440559148788452, "train_positive_predictive_value": 0.8581436276435852, "train_roc_auc": 0.9703967571258545, "train_sensitivity": 0.9533073902130127, "train_specificity": 0.8333333134651184, "epoch": 5, "step": 3000, "timestamp": 1760716062, "checkpoint_dir_name": "checkpoint_000005", "should_checkpoint": true, "done": false, "training_iteration": 6, "trial_id": "a46a968f", "date": "2025-10-17_18-47-44", "time_this_iter_s": 250.75776267051697, "time_total_s": 1653.26047873497, "pid": 337935, "hostname": "alex-MS-7996", "node_ip": "192.168.1.241", "config": {"train_loop_config": {"learning_rate": 5.822477020628017e-06, "batch_size": 2, "tile_config": "TileConfig(size=TileSize(width=50, height=50), overlap=25)"}}, "time_since_restore": 1653.26047873497, "iterations_since_restore": 6}
{"train_loss": 0.017265914008021355, "val_loss": 0.40823063254356384, "val_accuracy": 0.878125011920929, "val_f1_score": 0.8594087958335876, "val_f2_score": 0.8718549013137817, "val_f3_score": 0.8760840892791748, "val_negative_predictive_value": 0.9089887738227844, "val_positive_predictive_value": 0.8394365906715393, "val_roc_auc": 0.9530142545700073, "val_sensitivity": 0.8803545236587524, "val_specificity": 0.8764896988868713, "train_accuracy": 0.9079999923706055, "train_f1_score": 0.9135338068008423, "train_f2_score": 0.9389489889144897, "train_f3_score": 0.9477379322052002, "train_negative_predictive_value": 0.9504504799842834, "train_positive_predictive_value": 0.8741007447242737, "train_roc_auc": 0.9772301912307739, "train_sensitivity": 0.9566929340362549, "train_specificity": 0.857723593711853, "epoch": 6, "step": 3500, "timestamp": 1760716313, "checkpoint_dir_name": "checkpoint_000006", "should_checkpoint": true, "done": false, "training_iteration": 7, "trial_id": "a46a968f", "date": "2025-10-17_18-51-55", "time_this_iter_s": 251.2036280632019, "time_total_s": 1904.464106798172, "pid": 337935, "hostname": "alex-MS-7996", "node_ip": "192.168.1.241", "config": {"train_loop_config": {"learning_rate": 5.822477020628017e-06, "batch_size": 2, "tile_config": "TileConfig(size=TileSize(width=50, height=50), overlap=25)"}}, "time_since_restore": 1904.464106798172, "iterations_since_restore": 7}
{"train_loss": 0.2225707769393921, "val_loss": 0.47829583287239075, "val_accuracy": 0.8837500214576721, "val_f1_score": 0.8616071343421936, "val_f2_score": 0.8577777743339539, "val_f3_score": 0.8565088510513306, "val_negative_predictive_value": 0.89496248960495, "val_positive_predictive_value": 0.8680659532546997, "val_roc_auc": 0.9503145217895508, "val_sensitivity": 0.8552437424659729, "val_specificity": 0.9046587347984314, "train_accuracy": 0.9169999957084656, "train_f1_score": 0.9208770394325256, "train_f2_score": 0.9429910182952881, "train_f3_score": 0.950600266456604, "train_negative_predictive_value": 0.9538461565971375, "train_positive_predictive_value": 0.8862385153770447, "train_roc_auc": 0.9782265424728394, "train_sensitivity": 0.9583333134651184, "train_specificity": 0.875, "epoch": 7, "step": 4000, "timestamp": 1760716562, "checkpoint_dir_name": "checkpoint_000007", "should_checkpoint": true, "done": false, "training_iteration": 8, "trial_id": "a46a968f", "date": "2025-10-17_18-56-04", "time_this_iter_s": 249.321631193161, "time_total_s": 2153.785737991333, "pid": 337935, "hostname": "alex-MS-7996", "node_ip": "192.168.1.241", "config": {"train_loop_config": {"learning_rate": 5.822477020628017e-06, "batch_size": 2, "tile_config": "TileConfig(size=TileSize(width=50, height=50), overlap=25)"}}, "time_since_restore": 2153.785737991333, "iterations_since_restore": 8}
{"train_loss": 0.18823637068271637, "val_loss": 0.4393157660961151, "val_accuracy": 0.8706250190734863, "val_f1_score": 0.85850989818573, "val_f2_score": 0.8986834287643433, "val_f3_score": 0.9129233956336975, "val_negative_predictive_value": 0.939803421497345, "val_positive_predictive_value": 0.7989822030067444, "val_roc_auc": 0.9549299478530884, "val_sensitivity": 0.9276218414306641, "val_specificity": 0.8288190960884094, "train_accuracy": 0.9309999942779541, "train_f1_score": 0.9320197105407715, "train_f2_score": 0.9517102837562561, "train_f3_score": 0.9584599733352661, "train_negative_predictive_value": 0.9642105102539062, "train_positive_predictive_value": 0.9009523987770081, "train_roc_auc": 0.9847939014434814, "train_sensitivity": 0.9653061032295227, "train_specificity": 0.8980392217636108, "epoch": 8, "step": 4500, "timestamp": 1760716813, "checkpoint_dir_name": "checkpoint_000008", "should_checkpoint": true, "done": false, "training_iteration": 9, "trial_id": "a46a968f", "date": "2025-10-17_19-00-15", "time_this_iter_s": 250.5011842250824, "time_total_s": 2404.2869222164154, "pid": 337935, "hostname": "alex-MS-7996", "node_ip": "192.168.1.241", "config": {"train_loop_config": {"learning_rate": 5.822477020628017e-06, "batch_size": 2, "tile_config": "TileConfig(size=TileSize(width=50, height=50), overlap=25)"}}, "time_since_restore": 2404.2869222164154, "iterations_since_restore": 9}
{"train_loss": 0.017010368406772614, "val_loss": 0.44791924953460693, "val_accuracy": 0.8475000262260437, "val_f1_score": 0.8409387469291687, "val_f2_score": 0.904628336429596, "val_f3_score": 0.9280575513839722, "val_negative_predictive_value": 0.9569313526153564, "val_positive_predictive_value": 0.7526254653930664, "val_roc_auc": 0.9600157737731934, "val_sensitivity": 0.9527326226234436, "val_specificity": 0.7703142166137695, "train_accuracy": 0.9290000200271606, "train_f1_score": 0.9314009547233582, "train_f2_score": 0.9506903290748596, "train_f3_score": 0.9572989344596863, "train_negative_predictive_value": 0.9612902998924255, "train_positive_predictive_value": 0.9009345769882202, "train_roc_auc": 0.9840160012245178, "train_sensitivity": 0.9639999866485596, "train_specificity": 0.8939999938011169, "epoch": 9, "step": 5000, "timestamp": 1760717077, "checkpoint_dir_name": "checkpoint_000009", "should_checkpoint": true, "done": false, "training_iteration": 10, "trial_id": "a46a968f", "date": "2025-10-17_19-04-40", "time_this_iter_s": 264.9392297267914, "time_total_s": 2669.226151943207, "pid": 337935, "hostname": "alex-MS-7996", "node_ip": "192.168.1.241", "config": {"train_loop_config": {"learning_rate": 5.822477020628017e-06, "batch_size": 2, "tile_config": "TileConfig(size=TileSize(width=50, height=50), overlap=25)"}}, "time_since_restore": 2669.226151943207, "iterations_since_restore": 10}
